madrin/__init__.py
madrin/madrin.py
madrin-1.0.0.dist-info/LICENSE
madrin-1.0.0.dist-info/METADATA
madrin-1.0.0.dist-info/WHEEL
madrin-1.0.0.dist-info/top_level.txt
madrin-1.0.0.dist-info/RECORD
