Metadata-Version: 2.1
Name: madrin
Version: 1.0.0
Summary: A Neural Network Library
Home-page: https://github.com/manohar3000/Madrin-A_Neural_Network_Library
Author: Manohar
Author-email: manohargehlot3000@gmail.com
License: MIT
Classifier: License :: OSI Approved :: MIT License
Classifier: Programming Language :: Python
Classifier: Operating System :: OS Independent
Classifier: Intended Audience :: Developers
Classifier: Intended Audience :: Education
Classifier: Intended Audience :: Information Technology
Classifier: Intended Audience :: Science/Research
License-File: LICENSE
Requires-Dist: numpy
